<?xml version="1.0" encoding="utf-8"?><DEFECTS><DEFECT>
    <SFA>
      <FILEPATH>D:\软工\jackchen1349\3121005204\Project_1\src\cppjieba\</FILEPATH>
      <FILENAME>Unicode.hpp</FILENAME>
      <LINE>23</LINE>
      <COLUMN>2</COLUMN>
    </SFA>
    <DEFECTCODE>26495</DEFECTCODE>
    <DESCRIPTION>未初始化变量 cppjieba::Word::unicode_length。始终初始化成员变量(type.6)。</DESCRIPTION>
    <FUNCTION>cppjieba::Word::{ctor}</FUNCTION>
    <DECORATED>??0Word@cppjieba@@QEAA@AEBV?$basic_string@DU?$char_traits@D@std@@V?$allocator@D@2@@std@@I@Z</DECORATED>
    <FUNCLINE>23</FUNCLINE>
    <ADDITIONALINFO>
      <targetSymbol>cppjieba::Word::unicode_length</targetSymbol>
    </ADDITIONALINFO>
    <PATH></PATH>
  </DEFECT><DEFECT>
    <SFA>
      <FILEPATH>D:\软工\jackchen1349\3121005204\Project_1\src\cppjieba\</FILEPATH>
      <FILENAME>Trie.hpp</FILENAME>
      <LINE>19</LINE>
      <COLUMN>0</COLUMN>
    </SFA>
    <DEFECTCODE>26495</DEFECTCODE>
    <DESCRIPTION>未初始化变量 cppjieba::DictUnit::weight。始终初始化成员变量(type.6)。</DESCRIPTION>
    <FUNCTION>cppjieba::DictUnit::{ctor}</FUNCTION>
    <DECORATED>??0DictUnit@cppjieba@@QEAA@XZ</DECORATED>
    <FUNCLINE>19</FUNCLINE>
    <ADDITIONALINFO>
      <targetSymbol>cppjieba::DictUnit::weight</targetSymbol>
    </ADDITIONALINFO>
    <PATH></PATH>
  </DEFECT><DEFECT>
    <SFA>
      <FILEPATH>D:\软工\jackchen1349\3121005204\Project_1\src\</FILEPATH>
      <FILENAME>main.cpp</FILENAME>
      <LINE>71</LINE>
      <COLUMN>27</COLUMN>
    </SFA>
    <DEFECTCODE>26451</DEFECTCODE>
    <DESCRIPTION>算术溢出: 使用 4 字节值上的运算符 * ，然后将结果转换到 8 字节值。在调用运算符 * 之前将值强制转换为宽类型可避免溢出(io.2)。</DESCRIPTION>
    <FUNCTION>cosineSimilarity</FUNCTION>
    <DECORATED>?cosineSimilarity@@YANAEBV?$vector@V?$basic_string@DU?$char_traits@D@std@@V?$allocator@D@2@@std@@V?$allocator@V?$basic_string@DU?$char_traits@D@std@@V?$allocator@D@2@@std@@@2@@std@@0@Z</DECORATED>
    <FUNCLINE>43</FUNCLINE>
    <PATH></PATH>
  </DEFECT><DEFECT>
    <SFA>
      <FILEPATH>D:\软工\jackchen1349\3121005204\Project_1\src\</FILEPATH>
      <FILENAME>main.cpp</FILENAME>
      <LINE>72</LINE>
      <COLUMN>27</COLUMN>
    </SFA>
    <DEFECTCODE>26451</DEFECTCODE>
    <DESCRIPTION>算术溢出: 使用 4 字节值上的运算符 * ，然后将结果转换到 8 字节值。在调用运算符 * 之前将值强制转换为宽类型可避免溢出(io.2)。</DESCRIPTION>
    <FUNCTION>cosineSimilarity</FUNCTION>
    <DECORATED>?cosineSimilarity@@YANAEBV?$vector@V?$basic_string@DU?$char_traits@D@std@@V?$allocator@D@2@@std@@V?$allocator@V?$basic_string@DU?$char_traits@D@std@@V?$allocator@D@2@@std@@@2@@std@@0@Z</DECORATED>
    <FUNCLINE>43</FUNCLINE>
    <PATH></PATH>
  </DEFECT><DEFECT>
    <SFA>
      <FILEPATH>D:\软工\jackchen1349\3121005204\Project_1\src\</FILEPATH>
      <FILENAME>main.cpp</FILENAME>
      <LINE>73</LINE>
      <COLUMN>27</COLUMN>
    </SFA>
    <DEFECTCODE>26451</DEFECTCODE>
    <DESCRIPTION>算术溢出: 使用 4 字节值上的运算符 * ，然后将结果转换到 8 字节值。在调用运算符 * 之前将值强制转换为宽类型可避免溢出(io.2)。</DESCRIPTION>
    <FUNCTION>cosineSimilarity</FUNCTION>
    <DECORATED>?cosineSimilarity@@YANAEBV?$vector@V?$basic_string@DU?$char_traits@D@std@@V?$allocator@D@2@@std@@V?$allocator@V?$basic_string@DU?$char_traits@D@std@@V?$allocator@D@2@@std@@@2@@std@@0@Z</DECORATED>
    <FUNCLINE>43</FUNCLINE>
    <PATH></PATH>
  </DEFECT><DEFECT>
    <SFA>
      <FILEPATH>D:\软工\jackchen1349\3121005204\Project_1\src\cppjieba\limonp\</FILEPATH>
      <FILENAME>LocalVector.hpp</FILENAME>
      <LINE>95</LINE>
      <COLUMN>10</COLUMN>
    </SFA>
    <DEFECTCODE>6387</DEFECTCODE>
    <DESCRIPTION>"ptr_" 可以是 "0"。</DESCRIPTION>
    <FUNCTION>limonp::LocalVector&lt;unsigned int&gt;::reserve</FUNCTION>
    <DECORATED>?reserve@?$LocalVector@I@limonp@@QEAAX_K@Z</DECORATED>
    <FUNCLINE>87</FUNCLINE>
    <PROBABILITY>1</PROBABILITY>
    <RANK>4</RANK>
    <CATEGORY>
      <RULECATEGORY>mspft</RULECATEGORY>
    </CATEGORY>
    <PATH>
      <SFA>
        <FILEPATH>D:\软工\jackchen1349\3121005204\Project_1\src\cppjieba\limonp\</FILEPATH>
        <FILENAME>LocalVector.hpp</FILENAME>
        <LINE>88</LINE>
        <COLUMN>12</COLUMN>
        <KEYEVENT>
          <ID>1</ID>
          <KIND>branch</KIND>
          <IMPORTANCE>Full</IMPORTANCE>
          <MESSAGE>跳过此分支(假定“size&lt;=capacity_”为 false)</MESSAGE>
        </KEYEVENT>
      </SFA>
      <SFA>
        <FILEPATH>D:\软工\jackchen1349\3121005204\Project_1\src\cppjieba\limonp\</FILEPATH>
        <FILENAME>LocalVector.hpp</FILENAME>
        <LINE>91</LINE>
        <COLUMN>8</COLUMN>
      </SFA>
      <SFA>
        <FILEPATH>D:\软工\jackchen1349\3121005204\Project_1\src\cppjieba\limonp\</FILEPATH>
        <FILENAME>LocalVector.hpp</FILENAME>
        <LINE>93</LINE>
        <COLUMN>8</COLUMN>
      </SFA>
      <SFA>
        <FILEPATH>D:\软工\jackchen1349\3121005204\Project_1\src\cppjieba\limonp\</FILEPATH>
        <FILENAME>LocalVector.hpp</FILENAME>
        <LINE>94</LINE>
        <COLUMN>9</COLUMN>
      </SFA>
      <SFA>
        <FILEPATH>D:\软工\jackchen1349\3121005204\Project_1\src\cppjieba\limonp\</FILEPATH>
        <FILENAME>LocalVector.hpp</FILENAME>
        <LINE>95</LINE>
        <COLUMN>10</COLUMN>
        <KEYEVENT>
          <ID>2</ID>
          <KIND>declaration</KIND>
          <IMPORTANCE>Full</IMPORTANCE>
          <MESSAGE>“ptr_”是“memcpy”中的输出(在 c:\program files\microsoft visual studio\2022\community\vc\tools\msvc\14.33.31629\include\vcruntime_string.h:43 处声明)</MESSAGE>
        </KEYEVENT>
      </SFA>
      <SFA>
        <FILEPATH>D:\软工\jackchen1349\3121005204\Project_1\src\cppjieba\limonp\</FILEPATH>
        <FILENAME>LocalVector.hpp</FILENAME>
        <LINE>95</LINE>
        <COLUMN>10</COLUMN>
        <KEYEVENT>
          <ID>3</ID>
          <KIND>usage</KIND>
          <IMPORTANCE>Essential</IMPORTANCE>
          <MESSAGE>“ptr_”不应为 NULL，因为这与“memcpy”上的 SAL 批注不一致</MESSAGE>
        </KEYEVENT>
      </SFA>
    </PATH>
  </DEFECT><DEFECT>
    <SFA>
      <FILEPATH>D:\软工\jackchen1349\3121005204\Project_1\src\cppjieba\limonp\</FILEPATH>
      <FILENAME>LocalVector.hpp</FILENAME>
      <LINE>63</LINE>
      <COLUMN>12</COLUMN>
    </SFA>
    <DEFECTCODE>6387</DEFECTCODE>
    <DESCRIPTION>"ptr_" 可以是 "0"。</DESCRIPTION>
    <FUNCTION>limonp::LocalVector&lt;unsigned int&gt;::=</FUNCTION>
    <DECORATED>??4?$LocalVector@I@limonp@@QEAAAEAV01@AEBV01@@Z</DECORATED>
    <FUNCLINE>53</FUNCLINE>
    <PROBABILITY>1</PROBABILITY>
    <RANK>4</RANK>
    <CATEGORY>
      <RULECATEGORY>mspft</RULECATEGORY>
    </CATEGORY>
    <PATH>
      <SFA>
        <FILEPATH>D:\软工\jackchen1349\3121005204\Project_1\src\cppjieba\limonp\</FILEPATH>
        <FILENAME>LocalVector.hpp</FILENAME>
        <LINE>54</LINE>
        <COLUMN>9</COLUMN>
      </SFA>
      <SFA>
        <FILEPATH>D:\软工\jackchen1349\3121005204\Project_1\src\cppjieba\limonp\</FILEPATH>
        <FILENAME>LocalVector.hpp</FILENAME>
        <LINE>55</LINE>
        <COLUMN>10</COLUMN>
      </SFA>
      <SFA>
        <FILEPATH>D:\软工\jackchen1349\3121005204\Project_1\src\cppjieba\limonp\</FILEPATH>
        <FILENAME>LocalVector.hpp</FILENAME>
        <LINE>56</LINE>
        <COLUMN>14</COLUMN>
      </SFA>
      <SFA>
        <FILEPATH>D:\软工\jackchen1349\3121005204\Project_1\src\cppjieba\limonp\</FILEPATH>
        <FILENAME>LocalVector.hpp</FILENAME>
        <LINE>57</LINE>
        <COLUMN>19</COLUMN>
        <KEYEVENT>
          <ID>1</ID>
          <KIND>branch</KIND>
          <IMPORTANCE>Full</IMPORTANCE>
          <MESSAGE>跳过此分支(假定“vec.buffer_==vec.ptr_”为 false)</MESSAGE>
        </KEYEVENT>
      </SFA>
      <SFA>
        <FILEPATH>D:\软工\jackchen1349\3121005204\Project_1\src\cppjieba\limonp\</FILEPATH>
        <FILENAME>LocalVector.hpp</FILENAME>
        <LINE>61</LINE>
        <COLUMN>11</COLUMN>
      </SFA>
      <SFA>
        <FILEPATH>D:\软工\jackchen1349\3121005204\Project_1\src\cppjieba\limonp\</FILEPATH>
        <FILENAME>LocalVector.hpp</FILENAME>
        <LINE>63</LINE>
        <COLUMN>12</COLUMN>
        <KEYEVENT>
          <ID>2</ID>
          <KIND>declaration</KIND>
          <IMPORTANCE>Full</IMPORTANCE>
          <MESSAGE>“ptr_”是“memcpy”中的输出(在 c:\program files\microsoft visual studio\2022\community\vc\tools\msvc\14.33.31629\include\vcruntime_string.h:43 处声明)</MESSAGE>
        </KEYEVENT>
      </SFA>
      <SFA>
        <FILEPATH>D:\软工\jackchen1349\3121005204\Project_1\src\cppjieba\limonp\</FILEPATH>
        <FILENAME>LocalVector.hpp</FILENAME>
        <LINE>63</LINE>
        <COLUMN>12</COLUMN>
        <KEYEVENT>
          <ID>3</ID>
          <KIND>usage</KIND>
          <IMPORTANCE>Essential</IMPORTANCE>
          <MESSAGE>“ptr_”不应为 NULL，因为这与“memcpy”上的 SAL 批注不一致</MESSAGE>
        </KEYEVENT>
      </SFA>
    </PATH>
  </DEFECT><DEFECT>
    <SFA>
      <FILEPATH>D:\软工\jackchen1349\3121005204\Project_1\src\cppjieba\</FILEPATH>
      <FILENAME>KeywordExtractor.hpp</FILENAME>
      <LINE>20</LINE>
      <COLUMN>2</COLUMN>
    </SFA>
    <DEFECTCODE>26495</DEFECTCODE>
    <DESCRIPTION>未初始化变量 cppjieba::KeywordExtractor::Word::weight。始终初始化成员变量(type.6)。</DESCRIPTION>
    <FUNCTION>cppjieba::KeywordExtractor::Word::{ctor}</FUNCTION>
    <DECORATED>??0Word@KeywordExtractor@cppjieba@@QEAA@XZ</DECORATED>
    <FUNCLINE>20</FUNCLINE>
    <ADDITIONALINFO>
      <targetSymbol>cppjieba::KeywordExtractor::Word::weight</targetSymbol>
    </ADDITIONALINFO>
    <PATH></PATH>
  </DEFECT></DEFECTS>